{"FqCiu4YN+8VRbkd7K+8NVA==":"dscf2349-1080x1167.jpg","EOg3x11MaqMdlIyE39RMAg==":"1_uoqrhjfjozrtybm1mugu6g-1600x480.jpg","LGhs9HbcfJQmmItpUTs+Kg==":"1_uoqrhjfjozrtybm1mugu6g-1-1600x480.jpg","TEsxHHxWi2WCIqrmM/l5Pg==":"image1-359x359.jpg","UUvdfaR1Z8jgkHXnmEDzzw==":"20180810-141145-2000x1125.jpg","ItpsK6Hse+snkzxjJbxRAQ==":"image-6-compressed-1%20copy%202-2000x2015.jpg","iVSku4AvmZtzVoJNPgrdsg==":"img-6370-1080x1178.jpg","pcLJBwiwC/S6hpmSa/RFcQ==":"0602_water2-670x674.jpg","vkiaHsL7IVOLdpgB6bZ/FA==":"0602_water1-1140x641.jpg","yMq4B0zPqnYYZor0KaRCTA==":"20180810_141145%20copy-738x891.jpg","nvO39jIE2aE6p+kwt3u+zQ==":"wet%20image1-738x554.png","WCrZR3DuUURSSSCTYvLoGg==":"toc-192x107.png","px5qR+/erN7RLCcRB9EGBA==":"02.jpg","gN/5rEU/pGLW18XtXqcRYQ==":"background7.jpg","qj16klWrO8y2NMH/TvFmaQ==":"toc-1680x939.png","icPMuBLR1E0ZkR69vuv0pQ==":"0602_water1-824x463.jpg","4ZrdU3RA/TsFPy9rjBXxAA==":"0602_water1-362x204.jpg","n3MgciLgPA4YFHgtLFNHAA==":"screen%20shot%202021-06-13%20at%2012.14.51%20am-650x503.png","koChnz5PZ7s27b160KuLow==":"picture1-650x291.png","9E36Jl6Tlg7Nc7sbEhqRBw==":"newatlas1-300x300.jpg","l+3H58hB9fRwn38Zat+oEQ==":"newatlas1-1024x576.jpg","GykqZ8HHQsBrCe8PX7c8ew==":"phys_org-439x115.jpg","fnyIYfcaL584YA0Q1rqxEw==":"sciencedaily-wide-1000x500.jpg","fACjZgc9DGuV52Ow2eUITA==":"azosensors-853x488.png","FC40cIx2P3CAQ3umsKmfxg==":"cornell-chronicle-1050x256.png","AfY2nNBOTtlPpY1MozQc3Q==":"logo-inv-279x100.png","9z0fjCoqjJuPCf+nfv4FLQ==":"newatlas1-1-1024x576.jpg","8rPgIHof4QeI8qTvrRyyiA==":"azosensors-492x281.png","Un7LT76XJiqG0HffuAWEVQ==":"cornell-chronicle-492x120.png","tSx/pCSJEKlmOqdN/3SbyQ==":"nanowerk-logo.svg","hrCCW2syb074JerssRgRLQ==":"background1.jpg","mNwRYtzoFHhBbe6wvo3NdQ==":"newatlas1-492x277.jpg","ycbWHCWpaffzIXfL7j00bw==":"phys_org-1-439x115.jpg","Dknl7W8EkEfT/4XNgF3xpw==":"sciencedaily-wide-492x246.jpg","/A5Ujml0IHxdMdXgLXNVbw==":"94c2e7108dd9c0f9b2a7.gif","r5sbZcqQwimspglEu4FXIQ==":"download-236x120.png","NDSol2aVLy6RChEhjjhtYQ==":"logo-2-272x90.png","kcfooSj2bFVepAmhlzlyIw==":"mirage-news.svg","0BtOUOmWETzdEHsX5CF6nA==":"cornell_university_seal.svg-192x192.png","GP90d0uLR/LU08rF3c21YA==":"screen%20shot%202021-06-13%20at%209.14.54%20am-492x106.png","8LOUSpPpPd35OP22uPbCDQ==":"download%20(1)-283x178.png","E0u/fVMzMWpkaVNEzbZxsA==":"mbr-1920x1280.jpg","lYsWPtNt2D7KciAoUTmvRA==":"mbr-1920x1279.jpg","4gm/Vl7Us2krMRKcn9hQmw==":"mbr-1-1920x1280.jpg","GLvJ5KYXKghMe5a/tbJmkQ==":"1280px-wired_logo.svg-492x197.png","ZlX8+evW7RR1xY6+PjdgVQ==":"screen%20shot%202021-07-03%20at%208.40.24%20am-402x178.png","kl0AExwk9Z13gKiWgR0zIQ==":"sciencedaily-wide-1-492x246.jpg","g4QLgjCMA+pxpbLhX/IdCQ==":"download-1-236x120.png"}